{
    "members": [
        {
            "imgLogoUrl": "https://www.casatoscana.co.za/images/flogo-med.png",
            "businessName": "Casa Toscana", 
            "businessAddress": "5 Darlington Road, Lynnwood Manor, Pretoria, Gauteng",
            "businessTel": "+27 (0)82 971 3004",
            "businessURL": "https://www.casatoscana.co.za/index.php",
            "membershipLevel": "Silver"
        },
        {
            "imgLogoUrl": "https://www.casatoscana.co.za/images/flogo-med.png",
            "businessName": "Casa Toscana", 
            "businessAddress": "5 Darlington Road, Lynnwood Manor, Pretoria, Gauteng",
            "businessTel": "+27 (0)82 971 3004",
            "businessURL": "https://www.casatoscana.co.za/index.php",
            "membershipLevel": "Silver"
        },
        {
            "imgLogoUrl": "https://www.casatoscana.co.za/images/flogo-med.png",
            "businessName": "Casa Toscana", 
            "businessAddress": "5 Darlington Road, Lynnwood Manor, Pretoria, Gauteng",
            "businessTel": "+27 (0)82 971 3004",
            "businessURL": "https://www.casatoscana.co.za/index.php",
            "membershipLevel": "Silver"
        },
        {
            "imgLogoUrl": "https://www.casatoscana.co.za/images/flogo-med.png",
            "businessName": "Casa Toscana", 
            "businessAddress": "5 Darlington Road, Lynnwood Manor, Pretoria, Gauteng",
            "businessTel": "+27 (0)82 971 3004",
            "businessURL" : "https://www.casatoscana.co.za/index.php",
            "membershipLevel" : "Silver"
        },
        {
            "imgLogoUrl" : "https://www.casatoscana.co.za/images/flogo-med.png",
            "businessName" : "Casa Toscana", 
            "businessAddress" : "5 Darlington Road, Lynnwood Manor, Pretoria, Gauteng",
            "businessTel" : "+27 (0)82 971 3004",
            "businessURL" : "https://www.casatoscana.co.za/index.php",
            "membershipLevel" : "Silver"
        },
        {
            "imgLogoUrl" : "https://www.casatoscana.co.za/images/flogo-med.png",
            "businessName" : "Casa Toscana", 
            "businessAddress" : "5 Darlington Road, Lynnwood Manor, Pretoria, Gauteng",
            "businessTel" : "+27 (0)82 971 3004",
            "businessURL" : "https://www.casatoscana.co.za/index.php",
            "membershipLevel" : "Silver"
        },
        {
            "imgLogoUrl" : "https://www.casatoscana.co.za/images/flogo-med.png",
            "businessName" : "Casa Toscana", 
            "businessAddress" : "5 Darlington Road, Lynnwood Manor, Pretoria, Gauteng",
            "businessTel" : "+27 (0)82 971 3004",
            "businessURL" : "https://www.casatoscana.co.za/index.php",
            "membershipLevel" : "Silver"
        }
    ]
}